DARTS/DARTS.py
DARTS/__init__.py
DARTS/_version.py
DARTS/dataloader.py
DARTS/dense_unet_model.py
DARTS/loss_func.py
DARTS/perform_pred.py
DARTS/unet.py
DARTS/utils.py
DARTSeg-1.0.0.dist-info/LICENSE
DARTSeg-1.0.0.dist-info/METADATA
DARTSeg-1.0.0.dist-info/WHEEL
DARTSeg-1.0.0.dist-info/top_level.txt
DARTSeg-1.0.0.dist-info/RECORD
