Metadata-Version: 2.1
Name: DARTSeg
Version: 1.0.0
Summary: Package for Brain Segmentation
Home-page: https://github.com/NYUMedML/DARTS
Author: Razavian Lab
Author-email: ark576@nyu.edu
License: UNKNOWN
Platform: UNKNOWN
Classifier: Programming Language :: Python :: 3
Classifier: License :: OSI Approved :: GNU General Public License v3 (GPLv3)
Classifier: Operating System :: OS Independent
Requires-Python: >=3.6
